kpctl/__init__.py
kpctl/__main__.py
kpctl/bpmn/__init__.py
kpctl/bpmn/bpmn_documenter.py
kpctl/bpmn/bpmn_editor.py
kpctl/bpmn/bpmn_validator.py
kpctl/color_log_formatter.py
kpctl/configurator.py
kpctl/constants.py
kpctl/exceptions.py
kpctl/exec/__init__.py
kpctl/exec/curl.py
kpctl/exec/deployer.py
kpctl/local_cache.py
kpctl/xml_support.py
kpctl-3.2.5.dist-info/LICENSE
kpctl-3.2.5.dist-info/METADATA
kpctl-3.2.5.dist-info/WHEEL
kpctl-3.2.5.dist-info/entry_points.txt
kpctl-3.2.5.dist-info/RECORD
